Metadata-Version: 2.1
Name: global-tools-win
Version: 0.1.0
Summary: Batch tools running on Windows 10//Deneme Version
Home-page: UNKNOWN
Author: Ersse
Author-email: ms1msp0136@gmail.com
License: MIT
Keywords: Global_Tools_Win
Platform: UNKNOWN
Classifier: Development Status :: 5 - Production/Stable
Classifier: Intended Audience :: Developers
Classifier: License :: OSI Approved :: MIT License
Classifier: Programming Language :: Python :: 3
Classifier: Programming Language :: Python :: 3.5
